{
  "id": "behemoth-hippopotamus",
  "nombre": "Behemoth Hippopotamus",
  "nivelSummon": 7,
  "alineamiento": "N",
  "tamano": "Huge",
  "tipo": "animal",
  "subtipos": [],
  "plantillasPermitidas": [
    "chthonic",
    "fiery",
    "celestial",
    "entropic",
    "resolute"
  ],
  "iniciativa": 3,
  "sentidos": [
    "low-light vision"
  ],
  "percepcion": 12,
  "atributos": {
    "fuerza": 29,
    "destreza": 8,
    "constitucion": 20,
    "inteligencia": 2,
    "sabiduria": 13,
    "carisma": 5
  },
  "ca": {
    "normal": 23,
    "toque": 7,
    "desprevenido": 23,
    "detalle": "-1 Dex, +16 natural, -2 size"
  },
  "pg": {
    "maximos": 182,
    "formula": "(14d8+70)"
  },
  "salvaciones": {
    "fortaleza": 14,
    "reflejos": 8,
    "voluntad": 7
  },
  "velocidades": [
    {
      "tipo": "land",
      "valor": 50
    }
  ],
  "ataques": [
    {
      "id": "bite",
      "name": "Bite",
      "attackBonus": 17,
      "quantity": 1,
      "attackType": "MELEE",
      "damageComponents": [
        {
          "formula": "4d8+13",
          "damageType": "PIERCING",
          "multipliesOnCritical": true
        }
      ],
      "critical": {
        "threatRangeStart": 19,
        "multiplier": 2
      },
      "notes": [
        "grab"
      ]
    }
  ],
  "espacio": "15 ft.",
  "alcance": "15 ft.",
  "ataquesEspeciales": [],
  "defensasEspeciales": [],
  "notasTacticas": [],
  "habilidadesResumidas": [
    {
      "nombre": "Special Qualities",
      "resumen": "hold breath"
    },
    {
      "nombre": "Defensive Abilities",
      "resumen": "sweat"
    }
  ],
  "habilidadesCompletas": [
    {
      "nombre": "Special Qualities",
      "texto": "hold breath"
    },
    {
      "nombre": "Defensive Abilities",
      "texto": "sweat"
    }
  ],
  "fullStatBlock": "CR 10\nBehemoth Hippopotamus\nN Huge animal\nInit +3\nSenses low-light vision; Perception +12\nAC 23, touch 7, flat-footed 23 (-1 Dex, +16 natural, -2 size)\nhp 182 (14d8+70)\nFort +14, Ref +8, Will +7\nSpeed 50 ft.\nMelee bite +17 (4d8+13/19-20 plus grab)\nSpecial Attacks —\nSpecial Abilities none\nSpell-Like Abilities none\nSpecial Qualities hold breath\nDefensive Abilities sweat\nStatistics Str 29, Dex 8, Con 20, Int 2, Wis 13, Cha 5\nBase Atk +10; CMB +2125; CMD 3034\nEnvironment warm rivers\nOrganization solitary or bloat (2-8)\nTreasure none\nSource PFRPG Bestiary 2"
}
